ipasc_tool/__init__.py
ipasc_tool/api/BaseAdapter.py
ipasc_tool/api/__init__.py
ipasc_tool/api/adapters/DKFZ_CAMI_Experimental_System_Nrrd_File_Converter.py
ipasc_tool/api/adapters/__init__.py
ipasc_tool/core/DeviceMetaDataCreator.py
ipasc_tool/core/Metadata.py
ipasc_tool/core/PAData.py
ipasc_tool/core/__init__.py
ipasc_tool/iohandler/__init__.py
ipasc_tool/iohandler/file_reader.py
ipasc_tool/iohandler/file_writer.py
ipasc_tool/qualitycontrol/CompletenessChecker.py
ipasc_tool/qualitycontrol/ConsistencyChecker.py
ipasc_tool/qualitycontrol/PADataIntegrityCheck.py
ipasc_tool/qualitycontrol/__init__.py
ipasc_tool-0.1.3.dist-info/LICENSE
ipasc_tool-0.1.3.dist-info/METADATA
ipasc_tool-0.1.3.dist-info/WHEEL
ipasc_tool-0.1.3.dist-info/top_level.txt
ipasc_tool-0.1.3.dist-info/RECORD
