Metadata-Version: 2.1
Name: ipasc-tool
Version: 0.1.3
Summary: Standardised Data Access Tool of IPASC
Home-page: UNKNOWN
Author: International Photoacoustic Standardisation Consortium (IPASC)
License: MIT
Platform: UNKNOWN
Requires-Python: >=3.7
License-File: LICENSE
Requires-Dist: numpy
Requires-Dist: matplotlib
Requires-Dist: h5py
Requires-Dist: pynrrd
Requires-Dist: myst-parser
